{
 "cells": [
  {
   "cell_type": "markdown",
   "metadata": {},
   "source": [
    "变量作用域"
   ]
  },
  {
   "cell_type": "code",
   "execution_count": 1,
   "metadata": {},
   "outputs": [
    {
     "name": "stdout",
     "output_type": "stream",
     "text": [
      "3\n"
     ]
    },
    {
     "ename": "NameError",
     "evalue": "name 'b' is not defined",
     "output_type": "error",
     "traceback": [
      "\u001b[1;31m---------------------------------------------------------------------------\u001b[0m",
      "\u001b[1;31mNameError\u001b[0m                                 Traceback (most recent call last)",
      "Cell \u001b[1;32mIn[1], line 7\u001b[0m\n\u001b[0;32m      4\u001b[0m     \u001b[38;5;28mprint\u001b[39m(a)\n\u001b[0;32m      5\u001b[0m     \u001b[38;5;28mprint\u001b[39m(b)\n\u001b[1;32m----> 7\u001b[0m \u001b[43mf1\u001b[49m\u001b[43m(\u001b[49m\u001b[38;5;241;43m3\u001b[39;49m\u001b[43m)\u001b[49m\n",
      "Cell \u001b[1;32mIn[1], line 5\u001b[0m, in \u001b[0;36mf1\u001b[1;34m(a)\u001b[0m\n\u001b[0;32m      3\u001b[0m \u001b[38;5;28;01mdef\u001b[39;00m \u001b[38;5;21mf1\u001b[39m(a):\n\u001b[0;32m      4\u001b[0m     \u001b[38;5;28mprint\u001b[39m(a)\n\u001b[1;32m----> 5\u001b[0m     \u001b[38;5;28mprint\u001b[39m(\u001b[43mb\u001b[49m)\n",
      "\u001b[1;31mNameError\u001b[0m: name 'b' is not defined"
     ]
    }
   ],
   "source": [
    "# 一个函数，读取一个局部变量和一个全局变量\n",
    "\n",
    "# 当b未定义的时候会报错。\n",
    "\n",
    "def f1(a):\n",
    "    print(a)\n",
    "    print(b)\n",
    "\n",
    "f1(3)"
   ]
  },
  {
   "cell_type": "code",
   "execution_count": 2,
   "metadata": {},
   "outputs": [
    {
     "name": "stdout",
     "output_type": "stream",
     "text": [
      "3\n",
      "6\n"
     ]
    }
   ],
   "source": [
    "b = 6\n",
    "f1(3)"
   ]
  },
  {
   "cell_type": "code",
   "execution_count": 3,
   "metadata": {},
   "outputs": [
    {
     "name": "stdout",
     "output_type": "stream",
     "text": [
      "3\n"
     ]
    },
    {
     "ename": "UnboundLocalError",
     "evalue": "local variable 'b' referenced before assignment",
     "output_type": "error",
     "traceback": [
      "\u001b[1;31m---------------------------------------------------------------------------\u001b[0m",
      "\u001b[1;31mUnboundLocalError\u001b[0m                         Traceback (most recent call last)",
      "Cell \u001b[1;32mIn[3], line 9\u001b[0m\n\u001b[0;32m      6\u001b[0m     \u001b[38;5;28mprint\u001b[39m(b)\n\u001b[0;32m      7\u001b[0m     b \u001b[38;5;241m=\u001b[39m \u001b[38;5;241m6\u001b[39m\n\u001b[1;32m----> 9\u001b[0m \u001b[43mf2\u001b[49m\u001b[43m(\u001b[49m\u001b[38;5;241;43m3\u001b[39;49m\u001b[43m)\u001b[49m\n",
      "Cell \u001b[1;32mIn[3], line 6\u001b[0m, in \u001b[0;36mf2\u001b[1;34m(a)\u001b[0m\n\u001b[0;32m      4\u001b[0m \u001b[38;5;28;01mdef\u001b[39;00m \u001b[38;5;21mf2\u001b[39m(a):\n\u001b[0;32m      5\u001b[0m     \u001b[38;5;28mprint\u001b[39m(a)\n\u001b[1;32m----> 6\u001b[0m     \u001b[38;5;28mprint\u001b[39m(\u001b[43mb\u001b[49m)\n\u001b[0;32m      7\u001b[0m     b \u001b[38;5;241m=\u001b[39m \u001b[38;5;241m6\u001b[39m\n",
      "\u001b[1;31mUnboundLocalError\u001b[0m: local variable 'b' referenced before assignment"
     ]
    }
   ],
   "source": [
    "# 下列函数中先打印再赋值\n",
    "# 会报错\n",
    "\n",
    "b = 6\n",
    "def f2(a):\n",
    "    print(a)\n",
    "    print(b)\n",
    "    b = 6\n",
    "\n",
    "f2(3)\n"
   ]
  },
  {
   "cell_type": "code",
   "execution_count": 5,
   "metadata": {},
   "outputs": [
    {
     "name": "stdout",
     "output_type": "stream",
     "text": [
      "3\n",
      "6\n"
     ]
    }
   ],
   "source": [
    "b = 6\n",
    "def f3(a):\n",
    "    global b\n",
    "    print(a)\n",
    "    print(b)\n",
    "    b = 9\n",
    "\n",
    "f3(3)"
   ]
  },
  {
   "cell_type": "code",
   "execution_count": 6,
   "metadata": {},
   "outputs": [
    {
     "data": {
      "text/plain": [
       "9"
      ]
     },
     "execution_count": 6,
     "metadata": {},
     "output_type": "execute_result"
    }
   ],
   "source": [
    "b"
   ]
  },
  {
   "cell_type": "code",
   "execution_count": 7,
   "metadata": {},
   "outputs": [
    {
     "data": {
      "text/plain": [
       "30"
      ]
     },
     "execution_count": 7,
     "metadata": {},
     "output_type": "execute_result"
    }
   ],
   "source": [
    "b = 30\n",
    "b"
   ]
  },
  {
   "cell_type": "code",
   "execution_count": 8,
   "metadata": {},
   "outputs": [
    {
     "name": "stdout",
     "output_type": "stream",
     "text": [
      "  4           0 LOAD_GLOBAL              0 (print)\n",
      "              2 LOAD_FAST                0 (a)\n",
      "              4 CALL_FUNCTION            1\n",
      "              6 POP_TOP\n",
      "\n",
      "  5           8 LOAD_GLOBAL              0 (print)\n",
      "             10 LOAD_GLOBAL              1 (b)\n",
      "             12 CALL_FUNCTION            1\n",
      "             14 POP_TOP\n",
      "             16 LOAD_CONST               0 (None)\n",
      "             18 RETURN_VALUE\n"
     ]
    }
   ],
   "source": [
    "# 查看字节码\n",
    "\n",
    "from dis import dis\n",
    "\n",
    "dis(f1)"
   ]
  },
  {
   "cell_type": "code",
   "execution_count": 9,
   "metadata": {},
   "outputs": [
    {
     "name": "stdout",
     "output_type": "stream",
     "text": [
      "  5           0 LOAD_GLOBAL              0 (print)\n",
      "              2 LOAD_FAST                0 (a)\n",
      "              4 CALL_FUNCTION            1\n",
      "              6 POP_TOP\n",
      "\n",
      "  6           8 LOAD_GLOBAL              0 (print)\n",
      "             10 LOAD_FAST                1 (b)\n",
      "             12 CALL_FUNCTION            1\n",
      "             14 POP_TOP\n",
      "\n",
      "  7          16 LOAD_CONST               1 (6)\n",
      "             18 STORE_FAST               1 (b)\n",
      "             20 LOAD_CONST               0 (None)\n",
      "             22 RETURN_VALUE\n"
     ]
    }
   ],
   "source": [
    "dis(f2)"
   ]
  },
  {
   "cell_type": "code",
   "execution_count": null,
   "metadata": {},
   "outputs": [],
   "source": []
  }
 ],
 "metadata": {
  "kernelspec": {
   "display_name": "d2l",
   "language": "python",
   "name": "python3"
  },
  "language_info": {
   "codemirror_mode": {
    "name": "ipython",
    "version": 3
   },
   "file_extension": ".py",
   "mimetype": "text/x-python",
   "name": "python",
   "nbconvert_exporter": "python",
   "pygments_lexer": "ipython3",
   "version": "3.9.19"
  }
 },
 "nbformat": 4,
 "nbformat_minor": 2
}
